CHANGELOG.md
LICENSE
MANIFEST.in
Makefile
README.md
setup.cfg
setup.py
tox.ini
px_django_legate.egg-info/PKG-INFO
px_django_legate.egg-info/SOURCES.txt
px_django_legate.egg-info/dependency_links.txt
px_django_legate.egg-info/requires.txt
px_django_legate.egg-info/top_level.txt
pxd_legate/__init__.py
pxd_legate/admin.py
pxd_legate/apps.py
pxd_legate/backends.py
pxd_legate/conf.py
pxd_legate/exceptions.py
pxd_legate/models.py
pxd_legate/signals.py
pxd_legate/utils.py
pxd_legate/migrations/0001_initial.py
pxd_legate/migrations/__init__.py
pxd_legate/models/__init__.py
pxd_legate/models/gathered.py
pxd_legate/models/object_access.py
pxd_legate/services/__init__.py
pxd_legate/services/assigner.py
pxd_legate/services/checker.py
pxd_legate/services/gatherer.py
pxd_legate/services/registry.py